[{"_id":"6298e921c5ba2b11181f468d","_graphic":{"_offset":{"_top":"0","_left":"0"},"_isOverridingTheme":false,"_hideOnMobile":false,"_isFloatingGraphic":false,"_position":"bottom-right"},"_heroImage":{"_graphic":{"srcAdvanced":{"_setImagePerDeviceSize":false}},"_floatingGraphic":{"_offset":{"_top":"0","_left":"0"},"_position":"bottom-right","_hideOnMobile":false},"_isEnabled":false,"layout":"center","_contentWidth":70},"_backgroundImage":{"_size":"cover","_position":"center","_fixed":false,"_repeat":false},"_mobileBackgroundImage":{"_size":"cover","_position":"center","_fixed":false,"_repeat":false},"_boxMenu":{"srcAdvanced":{"_setImagePerDeviceSize":false},"_heroImage":{"_graphic":{"srcAdvanced":{"_setImagePerDeviceSize":false}},"layout":"center","_contentWidth":70},"_headerGraphic":{"_offset":{"_top":"0","_left":"0"},"_isOverridingTheme":false,"_hideOnMobile":false,"_isFloatingGraphic":false,"_position":"bottom-right"},"_backgroundImage":{"_size":"cover","_position":"center","_fixed":false,"_repeat":false},"_mobileBackgroundImage":{"_size":"cover","_position":"center","_fixed":false,"_repeat":false},"_itemsPerRowLarge":2,"_itemsPerRowMedium":2,"_shouldShowProgressBarsOnMenus":true,"_showCompletionStatusOnMenus":false,"_showCompletionStatusInFooter":false,"_isVerticalItemLayout":false,"itemCompletionText":"Complete"},"_coverMenu":{"srcAdvanced":{"_setImagePerDeviceSize":false},"_coverButtonText":"View","_shouldShowProgressBarsOnMenus":true,"nextButtonAriaLabel":"Next","prevButtonAriaLabel":"Previous","homeButtonAriaLabel":"Home"},"_mapMenu":{"_position":{"_left":50,"_top":50},"_defaultPointerWidth":0,"_menuImageWidth":1024,"_menuScrollableContainerMaxWidth":1024,"_pointerWidth":0,"_shouldShowTitleBar":true},"_playlistMenu":{"_graphic":{"srcAdvanced":{"_setImagePerDeviceSize":false}},"_backgroundImage":{"srcAdvanced":{"_setImagePerDeviceSize":false}},"_desktopBackgroundImage":{"_size":"cover","_position":"center","_fixed":false,"_repeat":false},"_mobileBackgroundImage":{"_size":"cover","_position":"center","_fixed":false,"_repeat":false},"_heroImage":{"_graphic":{"srcAdvanced":{"_setImagePerDeviceSize":false}},"_floatingGraphic":{"_offset":{"_top":"0","_left":"0"},"_position":"bottom-right","_hideOnMobile":false},"layout":"center","_contentWidth":70}},"_standardMenu":{"_heroImage":{"_graphic":{"srcAdvanced":{"_setImagePerDeviceSize":false}},"layout":"center","_contentWidth":70},"_headerGraphic":{"_offset":{"_top":"0","_left":"0"},"_isOverridingTheme":false,"_hideOnMobile":false,"_isFloatingGraphic":false,"_position":"bottom-right"},"_backgroundImage":{"_size":"cover","_position":"center","_fixed":false,"_repeat":false},"_mobileBackgroundImage":{"_size":"cover","_position":"center","_fixed":false,"_repeat":false},"_shouldShowProgressBarsOnMenus":true,"_shouldShowIconOnMenuItems":true},"_swipeMenu":{"_graphic":{"srcAdvanced":{"_setImagePerDeviceSize":false}},"_hoverGraphic":{"srcAdvanced":{"_setImagePerDeviceSize":false}},"_heroImage":{"_graphic":{"srcAdvanced":{"_setImagePerDeviceSize":false}},"layout":"center","_contentWidth":70},"_headerGraphic":{"_offset":{"_top":"0","_left":"0"},"_isOverridingTheme":false,"_hideOnMobile":false,"_isFloatingGraphic":false,"_position":"bottom-right"},"_backgroundImage":{"_size":"cover","_position":"center","_fixed":false,"_repeat":false},"_mobileBackgroundImage":{"_size":"cover","_position":"center","_fixed":false,"_repeat":false},"_shouldDisableDetailOnHover":false,"_shouldDisableItemScaling":false,"_shouldShowControlsOnBottom":false,"_shouldAlwaysShowItems":false,"_shouldShowControlsOnHover":false,"_shouldHideDisabledControl":false,"_shouldShowProgressBarsOnMenus":true,"nextButtonAriaLabel":"Next","prevButtonAriaLabel":"Previous"},"_contentLocking":{"_isEnabled":false,"_lockingType":"contentObject","_shouldDisableNotifyOnUnlock":false,"_requiredCompleteIds":[],"_requiredAmount":0},"_courseAssessment":{"_isAssessmentPage":false},"_search":{"_searchTagIds":[]},"_isEnabled":true,"_isHidden":false,"_isSnapShot":false,"_isTemplate":false,"_type":"page","_evolveTags":[],"title":"08.01.01 CreativeAnalytics_NormativeInsights_WelcomeToCreativeAnalytics","linkText":"View","isLinkIconRightPosition":false,"durationLabel":"Duration","_categories":[],"_hidePageHeader":false,"_pageCompletionMethod":"components","_completionComponentIds":[],"_courseId":"6298e921c5ba2b11181f4685","_parentId":"6298e921c5ba2b11181f4685","_sortOrder":0,"_createdBy":"6244e7f90b942f09896449de","__v":0,"_refId":"6133dc328cc45e0dca4fa895","displayTitle":"","htmlTitle":"","_createdAt":"2022-06-02T16:45:21.910Z","_updatedAt":"2022-08-01T18:41:45.769Z","_updatedBy":"6244e7f90b942f09896449de"}]
